<?xml version="1.0" encoding="utf-8"?>
<d2_documentset new_format="true">
	<object_name value="Issued Print Category 2 Documents"/>
	<title value="Issued Print Context for C2 Category 2 Documents"/>
	<subject value=""/>
	<authors/>
	<keywords/>
	<a_status value=""/>
	<a_content_type value=""/>
	<log_entry value=""/>
	<language_code value=""/>
	<dql_where value="category = 2"/>
	<order_no value="158"/>
	<dql_from>
		<repeating value="cd_controlled_doc"/>
	</dql_from>
	<group_names/>
	<application_names>
		<repeating value="OpenText Life Sciences Quality and Manufacturing Solution"/>
	</application_names>
	<user_agent value=""/>
	<parent_names>
		<repeating value="Issued Print"/>
	</parent_names>
	<parent_order_no>
		<repeating value="8"/>
	</parent_order_no>
	<lock_config value="F"/>
	<parents_config/>
</d2_documentset>